<?xml version="1.0"?>
<phpunit xmlns="https://schema.phpunit.de/coverage/1.0">
  <file name="ArticleController.php" path="/Http/Controllers/Api">
    <totals>
      <lines total="32" comments="0" code="32" executable="9" executed="0" percent="0.00"/>
      <methods count="1" tested="0" percent="0.00"/>
      <functions count="0" tested="0" percent="0"/>
      <classes count="1" tested="0" percent="0.00"/>
      <traits count="0" tested="0" percent="0"/>
    </totals>
    <class name="App\Http\Controllers\Api\ArticleController" start="9" executable="9" executed="0" crap="20">
      <namespace name="App\Http\Controllers\Api"/>
      <method name="index" signature="index(Illuminate\Http\Request $request)" start="11" end="30" crap="20" executable="9" executed="0" coverage="0"/>
    </class>
    <source>
      <line no="1">
        <token name="T_OPEN_TAG">&lt;?php</token>
      </line>
      <line no="2"/>
      <line no="3">
        <token name="T_NAMESPACE">namespace</token>
        <token name="T_WHITESPACE"> </token>
        <token name="T_NAME_QUALIFIED">App\Http\Controllers\Api</token>
        <token name="T_SEMICOLON">;</token>
      </line>
      <line no="4"/>
      <line no="5">
        <token name="T_USE">use</token>
        <token name="T_WHITESPACE"> </token>
        <token name="T_NAME_QUALIFIED">App\Http\Controllers\Controller</token>
        <token name="T_SEMICOLON">;</token>
      </line>
      <line no="6">
        <token name="T_USE">use</token>
        <token name="T_WHITESPACE"> </token>
        <token name="T_NAME_QUALIFIED">App\Models\Article</token>
        <token name="T_SEMICOLON">;</token>
      </line>
      <line no="7">
        <token name="T_USE">use</token>
        <token name="T_WHITESPACE"> </token>
        <token name="T_NAME_QUALIFIED">Illuminate\Http\Request</token>
        <token name="T_SEMICOLON">;</token>
      </line>
      <line no="8"/>
      <line no="9">
        <token name="T_CLASS">class</token>
        <token name="T_WHITESPACE"> </token>
        <token name="T_STRING">ArticleController</token>
        <token name="T_WHITESPACE"> </token>
        <token name="T_EXTENDS">extends</token>
        <token name="T_WHITESPACE"> </token>
        <token name="T_STRING">Controller</token>
      </line>
      <line no="10">
        <token name="T_OPEN_CURLY">{</token>
      </line>
      <line no="11">
        <token name="T_WHITESPACE">    </token>
        <token name="T_PUBLIC">public</token>
        <token name="T_WHITESPACE"> </token>
        <token name="T_FUNCTION">function</token>
        <token name="T_WHITESPACE"> </token>
        <token name="T_STRING">index</token>
        <token name="T_OPEN_BRACKET">(</token>
        <token name="T_STRING">Request</token>
        <token name="T_WHITESPACE"> </token>
        <token name="T_VARIABLE">$request</token>
        <token name="T_CLOSE_BRACKET">)</token>
      </line>
      <line no="12">
        <token name="T_WHITESPACE">    </token>
        <token name="T_OPEN_CURLY">{</token>
      </line>
      <line no="13">
        <token name="T_WHITESPACE">        </token>
        <token name="T_VARIABLE">$query</token>
        <token name="T_WHITESPACE"> </token>
        <token name="T_EQUAL">=</token>
        <token name="T_WHITESPACE"> </token>
        <token name="T_STRING">Article</token>
        <token name="T_DOUBLE_COLON">::</token>
        <token name="T_STRING">with</token>
        <token name="T_OPEN_BRACKET">(</token>
        <token name="T_OPEN_SQUARE">[</token>
        <token name="T_CONSTANT_ENCAPSED_STRING">'company'</token>
        <token name="T_COMMA">,</token>
        <token name="T_WHITESPACE"> </token>
        <token name="T_CONSTANT_ENCAPSED_STRING">'platform'</token>
        <token name="T_CLOSE_SQUARE">]</token>
        <token name="T_CLOSE_BRACKET">)</token>
        <token name="T_SEMICOLON">;</token>
      </line>
      <line no="14"/>
      <line no="15">
        <token name="T_WHITESPACE">        </token>
        <token name="T_IF">if</token>
        <token name="T_WHITESPACE"> </token>
        <token name="T_OPEN_BRACKET">(</token>
        <token name="T_VARIABLE">$request</token>
        <token name="T_OBJECT_OPERATOR">-&gt;</token>
        <token name="T_STRING">has</token>
        <token name="T_OPEN_BRACKET">(</token>
        <token name="T_CONSTANT_ENCAPSED_STRING">'company_id'</token>
        <token name="T_CLOSE_BRACKET">)</token>
        <token name="T_CLOSE_BRACKET">)</token>
        <token name="T_WHITESPACE"> </token>
        <token name="T_OPEN_CURLY">{</token>
      </line>
      <line no="16">
        <token name="T_WHITESPACE">            </token>
        <token name="T_VARIABLE">$query</token>
        <token name="T_OBJECT_OPERATOR">-&gt;</token>
        <token name="T_STRING">where</token>
        <token name="T_OPEN_BRACKET">(</token>
        <token name="T_CONSTANT_ENCAPSED_STRING">'company_id'</token>
        <token name="T_COMMA">,</token>
        <token name="T_WHITESPACE"> </token>
        <token name="T_VARIABLE">$request</token>
        <token name="T_OBJECT_OPERATOR">-&gt;</token>
        <token name="T_STRING">company_id</token>
        <token name="T_CLOSE_BRACKET">)</token>
        <token name="T_SEMICOLON">;</token>
      </line>
      <line no="17">
        <token name="T_WHITESPACE">        </token>
        <token name="T_CLOSE_CURLY">}</token>
      </line>
      <line no="18"/>
      <line no="19">
        <token name="T_WHITESPACE">        </token>
        <token name="T_IF">if</token>
        <token name="T_WHITESPACE"> </token>
        <token name="T_OPEN_BRACKET">(</token>
        <token name="T_VARIABLE">$request</token>
        <token name="T_OBJECT_OPERATOR">-&gt;</token>
        <token name="T_STRING">has</token>
        <token name="T_OPEN_BRACKET">(</token>
        <token name="T_CONSTANT_ENCAPSED_STRING">'platform_id'</token>
        <token name="T_CLOSE_BRACKET">)</token>
        <token name="T_CLOSE_BRACKET">)</token>
        <token name="T_WHITESPACE"> </token>
        <token name="T_OPEN_CURLY">{</token>
      </line>
      <line no="20">
        <token name="T_WHITESPACE">            </token>
        <token name="T_VARIABLE">$query</token>
        <token name="T_OBJECT_OPERATOR">-&gt;</token>
        <token name="T_STRING">where</token>
        <token name="T_OPEN_BRACKET">(</token>
        <token name="T_CONSTANT_ENCAPSED_STRING">'platform_id'</token>
        <token name="T_COMMA">,</token>
        <token name="T_WHITESPACE"> </token>
        <token name="T_VARIABLE">$request</token>
        <token name="T_OBJECT_OPERATOR">-&gt;</token>
        <token name="T_STRING">platform_id</token>
        <token name="T_CLOSE_BRACKET">)</token>
        <token name="T_SEMICOLON">;</token>
      </line>
      <line no="21">
        <token name="T_WHITESPACE">        </token>
        <token name="T_CLOSE_CURLY">}</token>
      </line>
      <line no="22"/>
      <line no="23">
        <token name="T_WHITESPACE">        </token>
        <token name="T_IF">if</token>
        <token name="T_WHITESPACE"> </token>
        <token name="T_OPEN_BRACKET">(</token>
        <token name="T_VARIABLE">$request</token>
        <token name="T_OBJECT_OPERATOR">-&gt;</token>
        <token name="T_STRING">has</token>
        <token name="T_OPEN_BRACKET">(</token>
        <token name="T_CONSTANT_ENCAPSED_STRING">'limit'</token>
        <token name="T_CLOSE_BRACKET">)</token>
        <token name="T_CLOSE_BRACKET">)</token>
        <token name="T_WHITESPACE"> </token>
        <token name="T_OPEN_CURLY">{</token>
      </line>
      <line no="24">
        <token name="T_WHITESPACE">            </token>
        <token name="T_VARIABLE">$query</token>
        <token name="T_OBJECT_OPERATOR">-&gt;</token>
        <token name="T_STRING">limit</token>
        <token name="T_OPEN_BRACKET">(</token>
        <token name="T_VARIABLE">$request</token>
        <token name="T_OBJECT_OPERATOR">-&gt;</token>
        <token name="T_STRING">limit</token>
        <token name="T_CLOSE_BRACKET">)</token>
        <token name="T_SEMICOLON">;</token>
      </line>
      <line no="25">
        <token name="T_WHITESPACE">        </token>
        <token name="T_CLOSE_CURLY">}</token>
      </line>
      <line no="26"/>
      <line no="27">
        <token name="T_WHITESPACE">        </token>
        <token name="T_VARIABLE">$articles</token>
        <token name="T_WHITESPACE"> </token>
        <token name="T_EQUAL">=</token>
        <token name="T_WHITESPACE"> </token>
        <token name="T_VARIABLE">$query</token>
        <token name="T_OBJECT_OPERATOR">-&gt;</token>
        <token name="T_STRING">orderBy</token>
        <token name="T_OPEN_BRACKET">(</token>
        <token name="T_CONSTANT_ENCAPSED_STRING">'published_at'</token>
        <token name="T_COMMA">,</token>
        <token name="T_WHITESPACE"> </token>
        <token name="T_CONSTANT_ENCAPSED_STRING">'desc'</token>
        <token name="T_CLOSE_BRACKET">)</token>
        <token name="T_OBJECT_OPERATOR">-&gt;</token>
        <token name="T_STRING">paginate</token>
        <token name="T_OPEN_BRACKET">(</token>
        <token name="T_LNUMBER">20</token>
        <token name="T_CLOSE_BRACKET">)</token>
        <token name="T_SEMICOLON">;</token>
      </line>
      <line no="28"/>
      <line no="29">
        <token name="T_WHITESPACE">        </token>
        <token name="T_RETURN">return</token>
        <token name="T_WHITESPACE"> </token>
        <token name="T_STRING">response</token>
        <token name="T_OPEN_BRACKET">(</token>
        <token name="T_CLOSE_BRACKET">)</token>
        <token name="T_OBJECT_OPERATOR">-&gt;</token>
        <token name="T_STRING">json</token>
        <token name="T_OPEN_BRACKET">(</token>
        <token name="T_VARIABLE">$articles</token>
        <token name="T_CLOSE_BRACKET">)</token>
        <token name="T_SEMICOLON">;</token>
      </line>
      <line no="30">
        <token name="T_WHITESPACE">    </token>
        <token name="T_CLOSE_CURLY">}</token>
      </line>
      <line no="31">
        <token name="T_CLOSE_CURLY">}</token>
      </line>
      <line no="32"/>
    </source>
  </file>
</phpunit>
